gym_drone/__init__.py
gym_drone/envs/__init__.py
gym_drone/envs/drone_env.py
gym_drone-0.0.3.dist-info/METADATA
gym_drone-0.0.3.dist-info/WHEEL
gym_drone-0.0.3.dist-info/top_level.txt
gym_drone-0.0.3.dist-info/RECORD
