Metadata-Version: 2.1
Name: gym-drone
Version: 0.0.3
Summary: A OpenAI Gym Env for drone
Home-page: UNKNOWN
License: UNKNOWN
Platform: UNKNOWN
Requires-Dist: gym
